<annotation>
	<folder>JPEGImages</folder>
	<filename>20220312094423897.jpg</filename>
	<path>E:\&#23011;&#26330;&#31519;&#29825;&#28888;&#26499;\&#37733;&#21095;&#22678;&#25652;&#25580;Brush2022\JPEGImages\Image_20220312094423367.jpg</path>
	<source>
		<database>Unknown</database>
	</source>
	<size>
		<width>640</width>
		<height>512</height>
		<depth>1</depth>
	</size>
	<segmented>0</segmented>
	<object>
		<name>nick</name>
		<pose>Unspecified</pose>
		<truncated>0</truncated>
		<difficult>0</difficult>
		<bndbox>
			<xmin>410</xmin>
			<ymin>239</ymin>
			<xmax>478</xmax>
			<ymax>293</ymax>
		</bndbox>
	</object>
	<object>
		<name>nick</name>
		<pose>Unspecified</pose>
		<truncated>0</truncated>
		<difficult>0</difficult>
		<bndbox>
			<xmin>398</xmin>
			<ymin>197</ymin>
			<xmax>439</xmax>
			<ymax>272</ymax>
		</bndbox>
	</object>
	<object>
		<name>blot</name>
		<pose>Unspecified</pose>
		<truncated>0</truncated>
		<difficult>0</difficult>
		<bndbox>
			<xmin>374</xmin>
			<ymin>207</ymin>
			<xmax>391</xmax>
			<ymax>227</ymax>
		</bndbox>
	</object>
	<object>
		<name>scratch</name>
		<pose>Unspecified</pose>
		<truncated>0</truncated>
		<difficult>0</difficult>
		<bndbox>
			<xmin>223</xmin>
			<ymin>185</ymin>
			<xmax>358</xmax>
			<ymax>313</ymax>
		</bndbox>
	</object>
</annotation>