<annotation>
	<folder>JPEGImages</folder>
	<filename>20220312093035277.jpg</filename>
	<path>E:\&#23011;&#26330;&#31519;&#29825;&#28888;&#26499;\&#37733;&#21095;&#22678;&#25652;&#25580;Brush2022\JPEGImages\Image_20220312093029997.jpg</path>
	<source>
		<database>Unknown</database>
	</source>
	<size>
		<width>640</width>
		<height>512</height>
		<depth>1</depth>
	</size>
	<segmented>0</segmented>
	<object>
		<name>hole</name>
		<pose>Unspecified</pose>
		<truncated>0</truncated>
		<difficult>0</difficult>
		<bndbox>
			<xmin>308</xmin>
			<ymin>225</ymin>
			<xmax>387</xmax>
			<ymax>310</ymax>
		</bndbox>
	</object>
	<object>
		<name>gap</name>
		<pose>Unspecified</pose>
		<truncated>0</truncated>
		<difficult>0</difficult>
		<bndbox>
			<xmin>369</xmin>
			<ymin>188</ymin>
			<xmax>542</xmax>
			<ymax>270</ymax>
		</bndbox>
	</object>
	<object>
		<name>gap</name>
		<pose>Unspecified</pose>
		<truncated>0</truncated>
		<difficult>0</difficult>
		<bndbox>
			<xmin>157</xmin>
			<ymin>265</ymin>
			<xmax>327</xmax>
			<ymax>349</ymax>
		</bndbox>
	</object>
</annotation>