<annotation>
	<folder>JPEGImages</folder>
	<filename>202203120906119167.jpg</filename>
	<path>E:\&#23011;&#26330;&#31519;&#29825;&#28888;&#26499;\&#37733;&#21095;&#22678;&#25652;&#25580;Brush2022\JPEGImages\Image_202203120906118637.jpg</path>
	<source>
		<database>Unknown</database>
	</source>
	<size>
		<width>640</width>
		<height>512</height>
		<depth>1</depth>
	</size>
	<segmented>0</segmented>
	<object>
		<name>scratch</name>
		<pose>Unspecified</pose>
		<truncated>0</truncated>
		<difficult>0</difficult>
		<bndbox>
			<xmin>262</xmin>
			<ymin>171</ymin>
			<xmax>385</xmax>
			<ymax>288</ymax>
		</bndbox>
	</object>
	<object>
		<name>gap</name>
		<pose>Unspecified</pose>
		<truncated>0</truncated>
		<difficult>0</difficult>
		<bndbox>
			<xmin>182</xmin>
			<ymin>92</ymin>
			<xmax>539</xmax>
			<ymax>425</ymax>
		</bndbox>
	</object>
	<object>
		<name>blot</name>
		<pose>Unspecified</pose>
		<truncated>0</truncated>
		<difficult>0</difficult>
		<bndbox>
			<xmin>415</xmin>
			<ymin>207</ymin>
			<xmax>444</xmax>
			<ymax>235</ymax>
		</bndbox>
	</object>
	<object>
		<name>bruise</name>
		<pose>Unspecified</pose>
		<truncated>0</truncated>
		<difficult>0</difficult>
		<bndbox>
			<xmin>382</xmin>
			<ymin>271</ymin>
			<xmax>407</xmax>
			<ymax>297</ymax>
		</bndbox>
	</object>
</annotation>