<annotation>
	<folder>JPEGImages</folder>
	<filename>202203120925499971.jpg</filename>
	<path>E:\&#23011;&#26330;&#31519;&#29825;&#28888;&#26499;\&#37733;&#21095;&#22678;&#25652;&#25580;Brush2022\JPEGImages\Image_202203120925495941.jpg</path>
	<source>
		<database>Unknown</database>
	</source>
	<size>
		<width>640</width>
		<height>512</height>
		<depth>1</depth>
	</size>
	<segmented>0</segmented>
	<object>
		<name>scratch</name>
		<pose>Unspecified</pose>
		<truncated>0</truncated>
		<difficult>0</difficult>
		<bndbox>
			<xmin>415</xmin>
			<ymin>285</ymin>
			<xmax>548</xmax>
			<ymax>423</ymax>
		</bndbox>
	</object>
	<object>
		<name>bruise</name>
		<pose>Unspecified</pose>
		<truncated>0</truncated>
		<difficult>0</difficult>
		<bndbox>
			<xmin>271</xmin>
			<ymin>276</ymin>
			<xmax>282</xmax>
			<ymax>290</ymax>
		</bndbox>
	</object>
	<object>
		<name>blot</name>
		<pose>Unspecified</pose>
		<truncated>0</truncated>
		<difficult>0</difficult>
		<bndbox>
			<xmin>440</xmin>
			<ymin>205</ymin>
			<xmax>471</xmax>
			<ymax>239</ymax>
		</bndbox>
	</object>
	<object>
		<name>nick</name>
		<pose>Unspecified</pose>
		<truncated>0</truncated>
		<difficult>0</difficult>
		<bndbox>
			<xmin>247</xmin>
			<ymin>123</ymin>
			<xmax>295</xmax>
			<ymax>202</ymax>
		</bndbox>
	</object>
	<object>
		<name>hole</name>
		<pose>Unspecified</pose>
		<truncated>0</truncated>
		<difficult>0</difficult>
		<bndbox>
			<xmin>320</xmin>
			<ymin>208</ymin>
			<xmax>415</xmax>
			<ymax>309</ymax>
		</bndbox>
	</object>
	<object>
		<name>gap</name>
		<pose>Unspecified</pose>
		<truncated>0</truncated>
		<difficult>0</difficult>
		<bndbox>
			<xmin>396</xmin>
			<ymin>219</ymin>
			<xmax>571</xmax>
			<ymax>354</ymax>
		</bndbox>
	</object>
	<object>
		<name>gap</name>
		<pose>Unspecified</pose>
		<truncated>0</truncated>
		<difficult>0</difficult>
		<bndbox>
			<xmin>160</xmin>
			<ymin>148</ymin>
			<xmax>341</xmax>
			<ymax>296</ymax>
		</bndbox>
	</object>
</annotation>