<annotation>
	<folder>JPEGImages</folder>
	<filename>20220312092655449.jpg</filename>
	<path>E:\&#23011;&#26330;&#31519;&#29825;&#28888;&#26499;\&#37733;&#21095;&#22678;&#25652;&#25580;Brush2022\JPEGImages\Image_20220312092653919.jpg</path>
	<source>
		<database>Unknown</database>
	</source>
	<size>
		<width>640</width>
		<height>512</height>
		<depth>1</depth>
	</size>
	<segmented>0</segmented>
	<object>
		<name>bruise</name>
		<pose>Unspecified</pose>
		<truncated>0</truncated>
		<difficult>0</difficult>
		<bndbox>
			<xmin>331</xmin>
			<ymin>164</ymin>
			<xmax>341</xmax>
			<ymax>174</ymax>
		</bndbox>
	</object>
	<object>
		<name>nick</name>
		<pose>Unspecified</pose>
		<truncated>0</truncated>
		<difficult>0</difficult>
		<bndbox>
			<xmin>490</xmin>
			<ymin>246</ymin>
			<xmax>500</xmax>
			<ymax>260</ymax>
		</bndbox>
	</object>
	<object>
		<name>blot</name>
		<pose>Unspecified</pose>
		<truncated>0</truncated>
		<difficult>0</difficult>
		<bndbox>
			<xmin>270</xmin>
			<ymin>216</ymin>
			<xmax>330</xmax>
			<ymax>272</ymax>
		</bndbox>
	</object>
</annotation>